README.md
setup.py
daniel_cavazos_sdk/__init__.py
daniel_cavazos_sdk/builder.py
daniel_cavazos_sdk/client.py
daniel_cavazos_sdk.egg-info/PKG-INFO
daniel_cavazos_sdk.egg-info/SOURCES.txt
daniel_cavazos_sdk.egg-info/dependency_links.txt
daniel_cavazos_sdk.egg-info/top_level.txt