Metadata-Version: 2.1
Name: daniel-cavazos-sdk
Version: 0.1.0
Summary: Accesses The One API
Author: Daniel Cavazos
Author-email: dcaazy@gmail.com
Keywords: sdk
Classifier: Programming Language :: Python :: 3
Classifier: License :: OSI Approved :: MIT License
Classifier: Operating System :: OS Independent
Requires-Python: >=3.6
